pysdrc/__init__.py
pysdrc/decoder.py
pysdrc/encoder.py
pysdrc/py.typed
pysdrc/circuitpython/__init__.py
pysdrc/circuitpython/transmitter.py
pysdrc/tests/__init__.py
pysdrc/tests/test_decoder.py
pysdrc/tests/test_encoder.py
pysdrc-1.0.1.dist-info/0BSD.txt
pysdrc-1.0.1.dist-info/LICENSE
pysdrc-1.0.1.dist-info/METADATA
pysdrc-1.0.1.dist-info/MIT.txt
pysdrc-1.0.1.dist-info/WHEEL
pysdrc-1.0.1.dist-info/top_level.txt
pysdrc-1.0.1.dist-info/RECORD
