Metadata-Version: 2.1
Name: pysdrc
Version: 1.0.1
Summary: Python Software Defined Remote Control
Home-page: https://github.com/Flameeyes/pysdrc
Author: Diego Elio Pettenò
Author-email: flameeyes@flameeyes.com
License: MIT
Keywords: remote control,ir,sirc
Platform: UNKNOWN
Classifier: Development Status :: 4 - Beta
Classifier: License :: OSI Approved :: MIT License
Classifier: Operating System :: OS Independent
Classifier: Programming Language :: Python
Classifier: Programming Language :: Python :: 3
Requires-Python: ~=3.7
Provides-Extra: dev
Requires-Dist: mypy ; extra == 'dev'
Requires-Dist: pre-commit ; extra == 'dev'
Requires-Dist: pytest-mypy ; extra == 'dev'
Requires-Dist: pytest-timeout (>=1.3.0) ; extra == 'dev'
Requires-Dist: pytest (>=6.0) ; extra == 'dev'
Requires-Dist: setuptools-scm ; extra == 'dev'
